frast/__init__.py
frast/main.py
frast-0.1.0.dist-info/entry_points.txt
frast-0.1.0.dist-info/WHEEL
frast-0.1.0.dist-info/METADATA
frast-0.1.0.dist-info/RECORD
