Metadata-Version: 2.1
Name: frast
Version: 0.1.0
Summary: 
Author: Jackson Greene
Author-email: jackson.greene@student.curtin.edu.com
Requires-Python: >=3.8,<4.0
Classifier: Programming Language :: Python :: 3
Classifier: Programming Language :: Python :: 3.10
Classifier: Programming Language :: Python :: 3.8
Classifier: Programming Language :: Python :: 3.9
Requires-Dist: requests[all] (>=2.27.1,<3.0.0)
Requires-Dist: typer[all] (>=0.4.1,<0.5.0)
